createstructure/__init__.py
createstructure-8.4.dist-info/METADATA
createstructure-8.4.dist-info/WHEEL
createstructure-8.4.dist-info/top_level.txt
createstructure-8.4.dist-info/zip-safe
createstructure-8.4.dist-info/RECORD
