Metadata-Version: 2.1
Name: createstructure
Version: 8.4
Summary: With this program, you can easily create a repository on GitHub :octocat: with a basic template, personalized for your use.
Home-page: https://github.com/createstructure/createstructure
Author: createstructure
License: GNU
Platform: linux_distibution
Requires-Python: >=3.7
Requires-Dist: DateTime (>=4.3)
Requires-Dist: PyGithub (>=1.54)
Requires-Dist: requests (>=2.24.0)
